[{"name":"江苏省","index":null,"level":null,"tag":null,"cityId":320000,"parentId":null,"backgroundVersion":null,"background":null,"productId":null,"cellStationId":null},{"name":"无锡","index":null,"level":null,"tag":null,"cityId":320200,"parentId":null,"backgroundVersion":null,"background":null,"productId":null,"cellStationId":null},{"name":"苏州","index":null,"level":null,"tag":null,"cityId":320500,"parentId":null,"backgroundVersion":null,"background":null,"productId":null,"cellStationId":null},{"name":"园区","index":null,"level":null,"tag":null,"cityId":320501,"parentId":null,"backgroundVersion":null,"background":null,"productId":null,"cellStationId":null},{"name":"常熟","index":null,"level":null,"tag":null,"cityId":320581,"parentId":null,"backgroundVersion":null,"background":null,"productId":null,"cellStationId":null},{"name":"张家港","index":null,"level":null,"tag":null,"cityId":320582,"parentId":null,"backgroundVersion":null,"background":null,"productId":null,"cellStationId":null},{"name":"昆山","index":null,"level":null,"tag":null,"cityId":320583,"parentId":null,"backgroundVersion":null,"background":null,"productId":null,"cellStationId":null},{"name":"吴江","index":null,"level":null,"tag":null,"cityId":320584,"parentId":null,"backgroundVersion":null,"background":null,"productId":null,"cellStationId":null},{"name":"太仓","index":null,"level":null,"tag":null,"cityId":320585,"parentId":null,"backgroundVersion":null,"background":null,"productId":null,"cellStationId":null},{"name":"镇江","index":null,"level":null,"tag":null,"cityId":321100,"parentId":null,"backgroundVersion":null,"background":null,"productId":null,"cellStationId":null},{"name":"城市通用","index":null,"level":null,"tag":null,"cityId":0,"parentId":null,"backgroundVersion":null,"background":null,"productId":null,"cellStationId":null}]